treesum/__init__.py
treesum/cli.py
treesum/convert.py
treesum/summarize.py
treesum-0.3.3.dist-info/METADATA
treesum-0.3.3.dist-info/WHEEL
treesum-0.3.3.dist-info/entry_points.txt
treesum-0.3.3.dist-info/top_level.txt
treesum-0.3.3.dist-info/RECORD
