Metadata-Version: 2.1
Name: treesum
Version: 0.3.3
Summary: Utility and library for summarizing trees.
Home-page: https://github.com/metov/treesum
Author: Azat Akhmetov
Author-email: azatinfo@yandex.com
Classifier: Development Status :: 3 - Alpha
Requires-Dist: docopt
Requires-Dist: metovlogs
